gwops_client/__init__.py
gwops_client/core.py
gwops_client/example_client.py
gwops_client/example_publish.py
gwops_client-0.0.1.dist-info/METADATA
gwops_client-0.0.1.dist-info/WHEEL
gwops_client-0.0.1.dist-info/top_level.txt
gwops_client-0.0.1.dist-info/RECORD
