Metadata-Version: 2.1
Name: gwops-client
Version: 0.0.1
Summary: gwops client
Author-email: mapenghui <maph@bao.ac.cn>
Classifier: Intended Audience :: Education
Classifier: Intended Audience :: Science/Research
Classifier: Topic :: Scientific/Engineering :: Astronomy
Classifier: Topic :: System :: Networking
Requires-Python: >=3.7
Requires-Dist: pika
